{
  "category": "street",
  "images": [
    {
      "src": "/images/photography/street/atlanta-traffic.jpg",
      "alt": "Atlanta skyline",
      "caption": "Atlanta's rising skyline from Jackson Street Bridge.",
      "location": "Atlanta",
      "country": "USA",
      "featured": 2
    },
    {
      "src": "/images/photography/street/guanajuato-street.jpg",
      "alt": "Guanajuato, Mexico colorful streets",
      "caption": "The narrow, colorful, and hilly streets of Guanajuato. My favorite Mexican city.",
      "location": "Guanajuato",
      "country": "Mexico",
      "featured": 6
    },
    {
      "src": "/images/photography/street/placeholder.svg",
      "alt": "Busy Tokyo street crossing",
      "caption": "Rush hour at Shibuya Crossing",
      "location": "Tokyo",
      "country": "Japan",
      "date": "2024-03-10"
    },
    {
      "src": "/images/photography/street/placeholder.svg",
      "alt": "Street vendor preparing food",
      "caption": "Morning market in Bangkok",
      "location": "Bangkok",
      "country": "Thailand",
      "date": "2023-11-05"
    },
    {
      "src": "/images/photography/street/placeholder.svg",
      "alt": "Cyclist in narrow alley",
      "caption": "Hidden streets of Amsterdam",
      "location": "Amsterdam",
      "country": "Netherlands",
      "date": "2023-08-14"
    }
  ],
  "order": 0
}
