{
  "category": "street",
  "images": [
    {
      "src": "/images/photography/street/us-atlanta-street-1.jpg",
      "alt": "Atlanta skyline",
      "caption": "Atlanta's rising skyline from Jackson Street Bridge.",
      "location": "Atlanta",
      "country": "United States",
      "featured": 2
    },
    {
      "src": "/images/photography/street/us-atlanta-street-2.jpg",
      "alt": "Dia de los muertos celebrations in Norcross, Georgia",
      "caption": "Dia de los muertos celebrations in Norcross.",
      "location": "Atlanta",
      "country": "United States",
      "featured": 5
    },
    {
      "src": "/images/photography/street/turkey-istanbul-street-12.jpg",
      "alt": "The streets of Istanbul, Turkey",
      "caption": "Cruise ship passing Maiden's Tower.",
      "location": "Istanbul",
      "country": "Turkey",
      "featured": 4
    },
    {
      "src": "/images/photography/street/turkey-istanbul-street-29.jpg",
      "alt": "Hagia Sophia mosque in Istanbul, Turkey",
      "caption": "Hagia Sophia mosque",
      "location": "Istanbul",
      "country": "Turkey",
      "featured": 6
    },
    {
      "src": "/images/photography/street/us-atlanta-street-3.jpg",
      "alt": "Dia de los muertos at Oakland Cemetary",
      "caption": "A stylish Catrina at the dia de los muertos festivities in Oakland Cemetery.",
      "location": "Atlanta",
      "country": "United States"
    },
    {
      "src": "/images/photography/street/turkey-istanbul-street-01.jpg",
      "alt": "The Golden Horn in Istanbul, Turkey",
      "caption": "Boats traveling the Golden Horn",
      "location": "Istanbul",
      "country": "Turkey"
    },
    {
      "src": "/images/photography/street/turkey-istanbul-street-02.jpg",
      "alt": "Taksim Square in Istanbul, Turkey",
      "caption": "Taksim Square at night",
      "location": "Istanbul",
      "country": "Turkey"
    },
    {
      "src": "/images/photography/street/turkey-istanbul-street-03.jpg",
      "alt": "Taksim Square in Istanbul, Turkey",
      "caption": "Markets around Taksim Square",
      "location": "Istanbul",
      "country": "Turkey"
    },
    {
      "src": "/images/photography/street/turkey-istanbul-street-04.jpg",
      "alt": "Taksim Square in Istanbul, Turkey",
      "caption": "Food vendors in Taksim Square",
      "location": "Istanbul",
      "country": "Turkey"
    },
    {
      "src": "/images/photography/street/turkey-istanbul-street-05.jpg",
      "alt": "İstiklal Avenue in Istanbul, Turkey",
      "caption": "Deliciousness along İstiklal Avenue",
      "location": "Istanbul",
      "country": "Turkey"
    },
    {
      "src": "/images/photography/street/turkey-istanbul-street-06.jpg",
      "alt": "İstiklal Avenue in Istanbul, Turkey",
      "caption": "İstiklal Avenue's iconic red tram",
      "location": "Istanbul",
      "country": "Turkey"
    },
    {
      "src": "/images/photography/street/turkey-istanbul-street-07.jpg",
      "alt": "The streets of Istanbul, Turkey",
      "caption": "Colorful and quiet neighborhoods",
      "location": "Istanbul",
      "country": "Turkey"
    },
    {
      "src": "/images/photography/street/turkey-istanbul-street-08.jpg",
      "alt": "The streets of Istanbul, Turkey",
      "caption": "The european side's narrow streets",
      "location": "Istanbul",
      "country": "Turkey"
    },
    {
      "src": "/images/photography/street/turkey-istanbul-street-09.jpg",
      "alt": "Uskudar in Istanbul, Turkey",
      "caption": "Uskudar's festive waterfront",
      "location": "Istanbul",
      "country": "Turkey"
    },
    {
      "src": "/images/photography/street/turkey-istanbul-street-10.jpg",
      "alt": "Kadıköy in Istanbul, Turkey",
      "caption": "The Kadıköy to Moda red tram",
      "location": "Istanbul",
      "country": "Turkey"
    },
    {
      "src": "/images/photography/street/turkey-istanbul-street-11.jpg",
      "alt": "Kadıköy in Istanbul, Turkey",
      "caption": "The asian side's tram in Kadıköy",
      "location": "Istanbul",
      "country": "Turkey"
    },
    {
      "src": "/images/photography/street/turkey-istanbul-street-13.jpg",
      "alt": "Bosphorus in Istanbul, Turkey",
      "caption": "The Blue Mosque from the Bosphorus",
      "location": "Istanbul",
      "country": "Turkey"
    },
    {
      "src": "/images/photography/street/turkey-istanbul-street-14.jpg",
      "alt": "Maiden's Tower in Istanbul, Turkey",
      "caption": "Sun setting behind Maiden's Tower",
      "location": "Istanbul",
      "country": "Turkey"
    },
    {
      "src": "/images/photography/street/turkey-istanbul-street-15.jpg",
      "alt": "Uskudar, Istanbul, Turkey",
      "caption": "Street vendors in Uskudar",
      "location": "Istanbul",
      "country": "Turkey"
    },
    {
      "src": "/images/photography/street/turkey-istanbul-street-16.jpg",
      "alt": "Uskudar, Istanbul, Turkey",
      "caption": "1453 - The fall of Constantinople",
      "location": "Istanbul",
      "country": "Turkey"
    },
    {
      "src": "/images/photography/street/turkey-istanbul-street-17.jpg",
      "alt": "Uskudar, Istanbul, Turkey",
      "caption": "Evening fishing in Uskudar",
      "location": "Istanbul",
      "country": "Turkey"
    },
    {
      "src": "/images/photography/street/turkey-istanbul-street-18.jpg",
      "alt": "Kadıköy, Istanbul, Turkey",
      "caption": "Kadıköy's beautiful streets",
      "location": "Istanbul",
      "country": "Turkey"
    },
    {
      "src": "/images/photography/street/turkey-istanbul-street-19.jpg",
      "alt": "Bosphorus, Istanbul, Turkey",
      "caption": "Cruising the Bosphorus",
      "location": "Istanbul",
      "country": "Turkey"
    },
    {
      "src": "/images/photography/street/turkey-istanbul-street-20.jpg",
      "alt": "Bosphorus, Istanbul, Turkey",
      "caption": "Residential neighborhood along the Bosphorus",
      "location": "Istanbul",
      "country": "Turkey"
    },
    {
      "src": "/images/photography/street/turkey-istanbul-street-21.jpg",
      "alt": "Balat, Istanbul, Turkey",
      "caption": "Colorful Balat",
      "location": "Istanbul",
      "country": "Turkey"
    },
    {
      "src": "/images/photography/street/turkey-istanbul-street-22.jpg",
      "alt": "Balat, Istanbul, Turkey",
      "caption": "Safe from the rain in Balat",
      "location": "Istanbul",
      "country": "Turkey"
    },
    {
      "src": "/images/photography/street/turkey-istanbul-street-23.jpg",
      "alt": "Balat, Istanbul, Turkey",
      "caption": "Balat's narrow and hilly streets",
      "location": "Istanbul",
      "country": "Turkey"
    },
    {
      "src": "/images/photography/street/turkey-istanbul-street-24.jpg",
      "alt": "Bosphorus, Istanbul, Turkey",
      "caption": "Across the Bosphorus",
      "location": "Istanbul",
      "country": "Turkey"
    },
    {
      "src": "/images/photography/street/turkey-istanbul-street-25.jpg",
      "alt": "Galata Tower, Istanbul, Turkey",
      "caption": "Galata Tower across the Golden Horn",
      "location": "Istanbul",
      "country": "Turkey"
    },
    {
      "src": "/images/photography/street/turkey-istanbul-street-26.jpg",
      "alt": "Golden Horn, Istanbul, Turkey",
      "caption": "Fishing the Golden Horn",
      "location": "Istanbul",
      "country": "Turkey"
    },
    {
      "src": "/images/photography/street/turkey-istanbul-street-27.jpg",
      "alt": "Hagia Sophia, Istanbul, Turkey",
      "caption": "Solitude before the Hagia Sophia",
      "location": "Istanbul",
      "country": "Turkey"
    },
    {
      "src": "/images/photography/street/turkey-istanbul-street-28.jpg",
      "alt": "Hagia Sophia, Istanbul, Turkey",
      "caption": "Morning bread at the Hagia Sophia",
      "location": "Istanbul",
      "country": "Turkey"
    },
    {
      "src": "/images/photography/street/turkey-istanbul-street-30.jpg",
      "alt": "Hagia Sophia, Istanbul, Turkey",
      "caption": "Lighting up the Hagia Sophia",
      "location": "Istanbul",
      "country": "Turkey"
    },
    {
      "src": "/images/photography/street/turkey-istanbul-street-31.jpg",
      "alt": "Sultanahmet Square, Istanbul, Turkey",
      "caption": "Morning walk along Sultanahmet Square",
      "location": "Istanbul",
      "country": "Turkey"
    },
    {
      "src": "/images/photography/street/turkey-istanbul-street-32.jpg",
      "alt": "Blue Mosque, Istanbul, Turkey",
      "caption": "The Blue Mosque's courtyard",
      "location": "Istanbul",
      "country": "Turkey"
    },
    {
      "src": "/images/photography/street/turkey-istanbul-street-33.jpg",
      "alt": "Blue Mosque of Istanbul, Turkey",
      "caption": "The Blue Mosque's beautiful facade",
      "location": "Istanbul",
      "country": "Turkey"
    },
    {
      "src": "/images/photography/street/turkey-istanbul-street-34.jpg",
      "alt": "Hagia Sophia,  Istanbul, Turkey",
      "caption": "The Hagia Sophia before sunrise and crowds",
      "location": "Istanbul",
      "country": "Turkey"
    },
    {
      "src": "/images/photography/street/turkey-istanbul-street-35.jpg",
      "alt": "Hagia Sophia, Istanbul, Turkey",
      "caption": "Inside the Hagia Sophia",
      "location": "Istanbul",
      "country": "Turkey"
    },
    {
      "src": "/images/photography/street/turkey-istanbul-street-36.jpg",
      "alt": "The streets of Istanbul, Turkey",
      "caption": "Lights never go out here",
      "location": "Istanbul",
      "country": "Turkey"
    },
    {
      "src": "/images/photography/street/turkey-istanbul-street-37.jpg",
      "alt": "Egyptian Bazaar, Istanbul, Turkey",
      "caption": "Any spice you need at the Egyptian Bazaar",
      "location": "Istanbul",
      "country": "Turkey"
    },
    {
      "src": "/images/photography/street/turkey-istanbul-street-38.jpg",
      "alt": "The streets of Istanbul, Turkey",
      "caption": "You're never far from Baklava and sweets",
      "location": "Istanbul",
      "country": "Turkey"
    },
    {
      "src": "/images/photography/street/turkey-istanbul-street-39.jpg",
      "alt": "The streets of Istanbul, Turkey",
      "caption": "Mountains of Turkish Delight at the Egyptian Bazaar",
      "location": "Istanbul",
      "country": "Turkey"
    }
  ],
  "order": 2
}
